README.md
setup.cfg
setup.py
picard_metrics_sqlite/__init__.py
picard_metrics_sqlite/__main__.py
picard_metrics_sqlite/main.py
picard_metrics_sqlite.egg-info/PKG-INFO
picard_metrics_sqlite.egg-info/SOURCES.txt
picard_metrics_sqlite.egg-info/dependency_links.txt
picard_metrics_sqlite.egg-info/entry_points.txt
picard_metrics_sqlite.egg-info/requires.txt
picard_metrics_sqlite.egg-info/top_level.txt
picard_metrics_sqlite/metrics/__init__.py
picard_metrics_sqlite/metrics/gatk_calculatecontamination.py
picard_metrics_sqlite/metrics/metrics_util.py
picard_metrics_sqlite/metrics/picard_collectalignmentsummarymetrics.py
picard_metrics_sqlite/metrics/picard_collecthsmetrics.py
picard_metrics_sqlite/metrics/picard_collectmultiplemetrics.py
picard_metrics_sqlite/metrics/picard_collectoxogmetrics.py
picard_metrics_sqlite/metrics/picard_collectrnaseqmetrics.py
picard_metrics_sqlite/metrics/picard_collecttargetedpcrmetrics.py
picard_metrics_sqlite/metrics/picard_collectwgsmetrics.py
picard_metrics_sqlite/metrics/picard_markduplicates.py
picard_metrics_sqlite/metrics/picard_validatesamfile.py